eurec4a_snd/L1_bufr.py
eurec4a_snd/L1_rs41.py
eurec4a_snd/__init__.py
eurec4a_snd/_helpers.py
eurec4a_snd/_thermo.py
eurec4a_snd/_version.py
eurec4a_snd/make_quicklooks_rs41.py
eurec4a_snd/config/__init__.py
eurec4a_snd/config/cfg_creator.py
eurec4a_snd/config/meta_information_template.ini
eurec4a_snd/examples/data/example_bufr309053.bfr
eurec4a_snd/examples/data/example_bufr309056.bfr
eurec4a_snd/examples/data/example_bufr309057.bfr
eurec4a_snd/examples/data/example_mw41.dat
eurec4a_snd/examples/data/example_mw41.nc
eurec4a_snd/interpolate/__init__.py
eurec4a_snd/interpolate/batch_interpolate_soundings.py
eurec4a_snd/interpolate/postprocessing.py
eurec4a_snd/visualize/__init__.py
eurec4a_snd/visualize/make_skewT_metpy.py
eurec4a_snd-2.1.5.dist-info/METADATA
eurec4a_snd-2.1.5.dist-info/WHEEL
eurec4a_snd-2.1.5.dist-info/entry_points.txt
eurec4a_snd-2.1.5.dist-info/top_level.txt
eurec4a_snd-2.1.5.dist-info/RECORD
