Metadata-Version: 2.1
Name: eurec4a-snd
Version: 2.1.5
Summary: Common EUREC4A sounding standard
Home-page: https://github.com/observingClouds/eurec4a_snd
Author: eurec4a folks
Author-email: 
License: UNKNOWN
Platform: UNKNOWN
Classifier: Programming Language :: Python :: 3
Classifier: License :: OSI Approved :: MIT License
Classifier: Operating System :: OS Independent
Requires-Python: >=3.6
Requires-Dist: pillow (>=6.0.0)
Requires-Dist: matplotlib (>=3.1.0)
Requires-Dist: basemap (>=1.2.0)
Requires-Dist: numpy (>=1.15.0)
Requires-Dist: netCDF4 (>=1.4.0)
Requires-Dist: metpy (>=0.10.0)
